Workbook

Sheet Project Overview
A1: Manufacturing Cost & Profitability Analysis
A2: Self-directed finance & analytics case study using illustrative manufacturing data. No company or Tesla data is used.
A4: Business Question
A5: How do changes in production volume, selling price, material cost, labor, variable overhead, and fixed costs affect manufacturing profitability—and which drivers deserve the most management attention?
A8: Base-case Revenue | C8: Operating Profit | E8: Operating Margin | G8: Break-even Units
A9: ='Unit Economics'!B11 | C9: ='Unit Economics'!B15 | E9: ='Unit Economics'!B16 | G9: ='Unit Economics'!B17
A12: Model Components
A13: Assumptions | B13: Driver inputs for volume, price, unit costs, and fixed costs.
A14: Unit Economics | B14: Contribution margin, break-even volume, operating profit, and margin of safety.
A15: Monthly Forecast | B15: Budget vs. illustrative actual performance and variance analysis.
A16: Scenario Analysis | B16: Downside, base, upside, and sensitivity analysis.
A17: Dashboards | B17: Executive, variance, and scenario views for management communication.

Sheet Assumptions
A1: Assumptions
A2: Editable driver inputs for the base manufacturing case.
A4: Driver | B4: Base Input | C4: Unit / Note
A5: Annual production / sales volume | B5: 120000 | C5: units
A6: Selling price per unit | B6: 420 | C6: $ / unit
A7: Material cost per unit | B7: 210 | C7: $ / unit
A8: Direct labor per unit | B8: 48 | C8: $ / unit
A9: Variable overhead per unit | B9: 25 | C9: $ / unit
A10: Variable selling cost per unit | B10: 10 | C10: $ / unit
A11: Annual fixed manufacturing costs | B11: 8500000 | C11: $ / year
A12: Annual fixed SG&A / other costs | B12: 4100000 | C12: $ / year
A15: Illustrative portfolio assumptions only — not sourced from Tesla or any employer.

Sheet Unit Economics
A1: Unit Economics
A2: Base-case manufacturing profitability and break-even economics.
A4: Metric | B4: Value | C4: Formula / Interpretation
A5: Selling price / unit | B5: ='Assumptions'!B6 | C5: Revenue per unit
A6: Material cost / unit | B6: ='Assumptions'!B7 | C6: Variable cost
A7: Direct labor / unit | B7: ='Assumptions'!B8 | C7: Variable cost
A8: Variable overhead / unit | B8: ='Assumptions'!B9 | C8: Variable cost
A9: Variable selling / unit | B9: ='Assumptions'!B10 | C9: Variable cost
A10: Total variable cost / unit | B10: =SUM(B6:B9) | C10: Sum of variable costs
A11: Contribution / unit | B11: =B5-B10 | C11: Price less variable cost
A12: Revenue | B12: ='Assumptions'!B5*B5 | C12: Annual volume × selling price
A13: Total variable cost | B13: ='Assumptions'!B5*B10 | C13: Annual volume × variable cost / unit
A14: Contribution margin | B14: =B11-B12 | C14: Revenue less total variable cost
A15: Total fixed costs | B15: ='Assumptions'!B11+'Assumptions'!B12 | C15: Fixed manufacturing + fixed SG&A
A16: Operating profit | B16: =B13-B14 | C16: Contribution margin less fixed costs
A17: Operating margin | B17: =B15/B11 | C17: Operating profit ÷ revenue
A18: Break-even units | B18: =B14/B10 | C18: Fixed costs ÷ contribution / unit
A19: Margin of safety | B19: =('Assumptions'!B5-B17)/'Assumptions'!B5 | C19: Excess volume above break-even

Sheet Monthly Forecast
A1: Monthly Forecast
A2: Budget vs. illustrative actual results and operating-profit variance.
A4: Month | B4: Budget Units | C4: Actual Units | D4: Budget Price | E4: Actual Price | F4: Budget Material / Unit | G4: Actual Material / Unit | H4: Budget Revenue | I4: Actual Revenue | J4: Budget Op Profit | K4: Actual Op Profit | L4: Profit Variance
A5: Jan | B5: 8500 | C5: 8200 | D5: ='Assumptions'!B6 | E5: 417 | F5: ='Assumptions'!B7 | G5: 214 | H5: =B5*D5 | I5: =C5*E5 | J5: =B5*(D5-(F5+'Assumptions'!B8+'Assumptions'!B9+'Assumptions'!B10))-('Assumptions'!B11+'Assumptions'!B12)/12 | K5: =C5*(E5-(G5+'Assumptions'!B8+'Assumptions'!B9+'Assumptions'!B10))-('Assumptions'!B11+'Assumptions'!B12)/12 | L5: =K5-J5
A6: Feb | B6: 9000 | C6: 8700 | D6: ='Assumptions'!B6 | E6: 418 | F6: ='Assumptions'!B7 | G6: 215 | H6: =B6*D6 | I6: =C6*E6 | J6: =B6*(D6-(F6+'Assumptions'!B8+'Assumptions'!B9+'Assumptions'!B10))-('Assumptions'!B11+'Assumptions'!B12)/12 | K6: =C6*(E6-(G6+'Assumptions'!B8+'Assumptions'!B9+'Assumptions'!B10))-('Assumptions'!B11+'Assumptions'!B12)/12 | L6: =K6-J6
A7: Mar | B7: 9500 | C7: 9300 | D7: ='Assumptions'!B6 | E7: 419 | F7: ='Assumptions'!B7 | G7: 214 | H7: =B7*D7 | I7: =C7*E7 | J7: =B7*(D7-(F7+'Assumptions'!B8+'Assumptions'!B9+'Assumptions'!B10))-('Assumptions'!B11+'Assumptions'!B12)/12 | K7: =C7*(E7-(G7+'Assumptions'!B8+'Assumptions'!B9+'Assumptions'!B10))-('Assumptions'!B11+'Assumptions'!B12)/12 | L7: =K7-J7
A8: Apr | B8: 9500 | C8: 8800 | D8: ='Assumptions'!B6 | E8: 416 | F8: ='Assumptions'!B7 | G8: 216 | H8: =B8*D8 | I8: =C8*E8 | J8: =B8*(D8-(F8+'Assumptions'!B8+'Assumptions'!B9+'Assumptions'!B10))-('Assumptions'!B11+'Assumptions'!B12)/12 | K8: =C8*(E8-(G8+'Assumptions'!B8+'Assumptions'!B9+'Assumptions'!B10))-('Assumptions'!B11+'Assumptions'!B12)/12 | L8: =K8-J8
A9: May | B9: 10000 | C9: 9500 | D9: ='Assumptions'!B6 | E9: 417 | F9: ='Assumptions'!B7 | G9: 218 | H9: =B9*D9 | I9: =C9*E9 | J9: =B9*(D9-(F9+'Assumptions'!B8+'Assumptions'!B9+'Assumptions'!B10))-('Assumptions'!B11+'Assumptions'!B12)/12 | K9: =C9*(E9-(G9+'Assumptions'!B8+'Assumptions'!B9+'Assumptions'!B10))-('Assumptions'!B11+'Assumptions'!B12)/12 | L9: =K9-J9
A10: Jun | B10: 10000 | C10: 9000 | D10: ='Assumptions'!B6 | E10: 415 | F10: ='Assumptions'!B7 | G10: 219 | H10: =B10*D10 | I10: =C10*E10 | J10: =B10*(D10-(F10+'Assumptions'!B8+'Assumptions'!B9+'Assumptions'!B10))-('Assumptions'!B11+'Assumptions'!B12)/12 | K10: =C10*(E10-(G10+'Assumptions'!B8+'Assumptions'!B9+'Assumptions'!B10))-('Assumptions'!B11+'Assumptions'!B12)/12 | L10: =K10-J10
A11: Jul | B11: 10000 | C11: 8600 | D11: ='Assumptions'!B6 | E11: 414 | F11: ='Assumptions'!B7 | G11: 221 | H11: =B11*D11 | I11: =C11*E11 | J11: =B11*(D11-(F11+'Assumptions'!B8+'Assumptions'!B9+'Assumptions'!B10))-('Assumptions'!B11+'Assumptions'!B12)/12 | K11: =C11*(E11-(G11+'Assumptions'!B8+'Assumptions'!B9+'Assumptions'!B10))-('Assumptions'!B11+'Assumptions'!B12)/12 | L11: =K11-J11
A12: Aug | B12: 10500 | C12: 10200 | D12: ='Assumptions'!B6 | E12: 418 | F12: ='Assumptions'!B7 | G12: 218 | H12: =B12*D12 | I12: =C12*E12 | J12: =B12*(D12-(F12+'Assumptions'!B8+'Assumptions'!B9+'Assumptions'!B10))-('Assumptions'!B11+'Assumptions'!B12)/12 | K12: =C12*(E12-(G12+'Assumptions'!B8+'Assumptions'!B9+'Assumptions'!B10))-('Assumptions'!B11+'Assumptions'!B12)/12 | L12: =K12-J12
A13: Sep | B13: 10500 | C13: 10500 | D13: ='Assumptions'!B6 | E13: 419 | F13: ='Assumptions'!B7 | G13: 216 | H13: =B13*D13 | I13: =C13*E13 | J13: =B13*(D13-(F13+'Assumptions'!B8+'Assumptions'!B9+'Assumptions'!B10))-('Assumptions'!B11+'Assumptions'!B12)/12 | K13: =C13*(E13-(G13+'Assumptions'!B8+'Assumptions'!B9+'Assumptions'!B10))-('Assumptions'!B11+'Assumptions'!B12)/12 | L13: =K13-J13
A14: Oct | B14: 10500 | C14: 11100 | D14: ='Assumptions'!B6 | E14: 421 | F14: ='Assumptions'!B7 | G14: 214 | H14: =B14*D14 | I14: =C14*E14 | J14: =B14*(D14-(F14+'Assumptions'!B8+'Assumptions'!B9+'Assumptions'!B10))-('Assumptions'!B11+'Assumptions'!B12)/12 | K14: =C14*(E14-(G14+'Assumptions'!B8+'Assumptions'!B9+'Assumptions'!B10))-('Assumptions'!B11+'Assumptions'!B12)/12 | L14: =K14-J14
A15: Nov | B15: 10000 | C15: 10800 | D15: ='Assumptions'!B6 | E15: 422 | F15: ='Assumptions'!B7 | G15: 213 | H15: =B15*D15 | I15: =C15*E15 | J15: =B15*(D15-(F15+'Assumptions'!B8+'Assumptions'!B9+'Assumptions'!B10))-('Assumptions'!B11+'Assumptions'!B12)/12 | K15: =C15*(E15-(G15+'Assumptions'!B8+'Assumptions'!B9+'Assumptions'!B10))-('Assumptions'!B11+'Assumptions'!B12)/12 | L15: =K15-J15
A16: Dec | B16: 10000 | C16: 11100 | D16: ='Assumptions'!B6 | E16: 422 | F16: ='Assumptions'!B7 | G16: 212 | H16: =B16*D16 | I16: =C16*E16 | J16: =B16*(D16-(F16+'Assumptions'!B8+'Assumptions'!B9+'Assumptions'!B10))-('Assumptions'!B11+'Assumptions'!B12)/12 | K16: =C16*(E16-(G16+'Assumptions'!B8+'Assumptions'!B9+'Assumptions'!B10))-('Assumptions'!B11+'Assumptions'!B12)/12 | L16: =K16-J16
A18: TOTAL | B18: =SUM(B5:B16) | C18: =SUM(C5:C16) | H18: =SUM(H5:H16) | I18: =SUM(I5:I16) | J18: =SUM(J5:J16) | K18: =SUM(K5:K16) | L18: =SUM(L5:L16)

Sheet Scenario Analysis
A1: Scenario Analysis
A2: Downside, base, upside, and individual profitability sensitivities.
A4: Driver | B4: Downside | C4: Base | D4: Upside
A5: Volume | B5: 100000 | C5: 120000 | D5: 135000
A6: Price / unit | B6: 400 | C6: 420 | D6: 430
A7: Material / unit | B7: 225 | C7: 210 | D7: 202
A8: Labor / unit | B8: 52 | C8: 48 | D8: 47
A9: Variable OH / unit | B9: 28 | C9: 25 | D9: 24
A10: Variable selling / unit | B10: 10 | C10: 10 | D10: 10
A11: Fixed costs | B11: 13000000 | C11: 12600000 | D11: 12350000
A13: Metric | B13: Downside | C13: Base | D13: Upside
A14: Revenue | B14: =B5*B6 | C14: =C5*C6 | D14: =D5*D6
A15: Variable cost / unit | B15: =B7+B8+B9+B10 | C15: =C7+C8+C9+C10 | D15: =D7+D8+D9+D10
A16: Operating profit | B16: =B5*(B6-B15)-B11 | C16: =C5*(C6-C15)-C11 | D16: =D5*(D6-D15)-D11
A17: Operating margin | B17: =B16/B14 | C17: =C16/C14 | D17: =D16/D14
A18: Break-even units | B18: =B11/(B6-B15) | C18: =C11/(C6-C15) | D18: =D11/(D6-D15)
A21: Sensitivity Lever | B21: Change | C21: Annual Op Profit Impact
A22: Volume | B22: +10,000 units | C22: =10000*('Unit Economics'!B10)
A23: Material cost | B23: -$5 / unit | C23: ='Assumptions'!B5*5
A24: Selling price | B24: +1% | C24: ='Assumptions'!B5*'Assumptions'!B6*1%
A25: Fixed costs | B25: -$500,000 | C25: =500000

Sheet Dashboard
A1: Executive Performance Dashboard
A2: Management view of profitability, break-even economics, scenarios, and key sensitivities.
A4: Revenue | C4: Operating Profit | E4: Operating Margin | G4: Break-even Units
A5: ='Unit Economics'!B11 | C5: ='Unit Economics'!B15 | E5: ='Unit Economics'!B16 | G5: ='Unit Economics'!B17
A9: Scenario | B9: Operating Profit | D9: Scenario | E9: Break-even Units
A10: Downside | B10: ='Scenario Analysis'!B16 | D10: Downside | E10: ='Scenario Analysis'!B18
A11: Base | B11: ='Scenario Analysis'!C16 | D11: Base | E11: ='Scenario Analysis'!C18
A12: Upside | B12: ='Scenario Analysis'!D16 | D12: Upside | E12: ='Scenario Analysis'!D18

Sheet Variance Dashboard
A1: Budget vs. Actual Variance Dashboard
A2: Monthly performance view highlighting revenue and operating-profit divergence from plan.
A4: Budget Op Profit | C4: Actual Op Profit | E4: Profit Variance | G4: Actual Units
A5: ='Monthly Forecast'!J18 | C5: ='Monthly Forecast'!K18 | E5: ='Monthly Forecast'!L18 | G5: ='Monthly Forecast'!C18
A9: Month | B9: Budget Op Profit | C9: Actual Op Profit
A10: ='Monthly Forecast'!A5 | B10: ='Monthly Forecast'!J5 | C10: ='Monthly Forecast'!K5
A11: ='Monthly Forecast'!A6 | B11: ='Monthly Forecast'!J6 | C11: ='Monthly Forecast'!K6
A12: ='Monthly Forecast'!A7 | B12: ='Monthly Forecast'!J7 | C12: ='Monthly Forecast'!K7
A13: ='Monthly Forecast'!A8 | B13: ='Monthly Forecast'!J8 | C13: ='Monthly Forecast'!K8
A14: ='Monthly Forecast'!A9 | B14: ='Monthly Forecast'!J9 | C14: ='Monthly Forecast'!K9
A15: ='Monthly Forecast'!A10 | B15: ='Monthly Forecast'!J10 | C15: ='Monthly Forecast'!K10
A16: ='Monthly Forecast'!A11 | B16: ='Monthly Forecast'!J11 | C16: ='Monthly Forecast'!K11
A17: ='Monthly Forecast'!A12 | B17: ='Monthly Forecast'!J12 | C17: ='Monthly Forecast'!K12
A18: ='Monthly Forecast'!A13 | B18: ='Monthly Forecast'!J13 | C18: ='Monthly Forecast'!K13
A19: ='Monthly Forecast'!A14 | B19: ='Monthly Forecast'!J14 | C19: ='Monthly Forecast'!K14
A20: ='Monthly Forecast'!A15 | B20: ='Monthly Forecast'!J15 | C20: ='Monthly Forecast'!K15
A21: ='Monthly Forecast'!A16 | B21: ='Monthly Forecast'!J16 | C21: ='Monthly Forecast'!K16

Sheet Scenario Dashboard
A1: Scenario & Sensitivity Dashboard
A2: Decision-support view of the operating levers with the largest modeled profit impact.
A4: Sensitivity Lever | B4: Change | C4: Annual Op Profit Impact
A5: ='Scenario Analysis'!A22 | B5: ='Scenario Analysis'!B22 | C5: ='Scenario Analysis'!C22
A6: ='Scenario Analysis'!A23 | B6: ='Scenario Analysis'!B23 | C6: ='Scenario Analysis'!C23
A7: ='Scenario Analysis'!A24 | B7: ='Scenario Analysis'!B24 | C7: ='Scenario Analysis'!C24
A8: ='Scenario Analysis'!A25 | B8: ='Scenario Analysis'!B25 | C8: ='Scenario Analysis'!C25
A30: Portfolio note: All values are illustrative case-study data and are not Tesla or employer data.
